mysql_on_sockets/__init__.py
mysql_on_sockets/mysql_on_sockets.py
mysql_on_sockets-0.0.1.dist-info/LICENSE.txt
mysql_on_sockets-0.0.1.dist-info/METADATA
mysql_on_sockets-0.0.1.dist-info/WHEEL
mysql_on_sockets-0.0.1.dist-info/top_level.txt
mysql_on_sockets-0.0.1.dist-info/RECORD
