Metadata-Version: 2.1
Name: mysql-on-sockets
Version: 0.0.1
Summary: A module which helps you access your MYSQL database over local network.
Author: Vedant Barhate
Author-email: vedant.barhate27@gmail.com
Keywords: python,socket,sockets,mysql,sql,database,server-client,remote user
Classifier: Development Status :: 1 - Planning
Classifier: Intended Audience :: Developers
Classifier: Programming Language :: Python :: 3
Classifier: Operating System :: Unix
Classifier: Operating System :: MacOS :: MacOS X
Classifier: Operating System :: Microsoft :: Windows
Classifier: License :: OSI Approved :: MIT License
License-File: LICENSE.txt
Requires-Dist: mysql.connector
Requires-Dist: datetime
